README.txt
setup.cfg
setup.py
docs/HISTORY.txt
docs/INSTALL.txt
docs/LICENSE.GPL
docs/LICENSE.txt
src/actionbar/__init__.py
src/actionbar.babble.egg-info/PKG-INFO
src/actionbar.babble.egg-info/SOURCES.txt
src/actionbar.babble.egg-info/dependency_links.txt
src/actionbar.babble.egg-info/entry_points.txt
src/actionbar.babble.egg-info/namespace_packages.txt
src/actionbar.babble.egg-info/not-zip-safe
src/actionbar.babble.egg-info/paster_plugins.txt
src/actionbar.babble.egg-info/requires.txt
src/actionbar.babble.egg-info/top_level.txt
src/actionbar/babble/__init__.py
src/actionbar/babble/configure.zcml
src/actionbar/babble/tests.py
src/actionbar/babble/browser/__init__.py
src/actionbar/babble/browser/chat.py
src/actionbar/babble/browser/configure.zcml
src/actionbar/babble/browser/interfaces.py
src/actionbar/babble/browser/viewlets.py
src/actionbar/babble/browser/javascript/babblefeeder.js
src/actionbar/babble/browser/stylesheets/babblefeeder.css
src/actionbar/babble/browser/templates/chat_viewlet.pt
src/actionbar/babble/browser/templates/onlinecontacts.pt
src/actionbar/babble/profiles/default/browserlayer.xml
src/actionbar/babble/profiles/default/cssregistry.xml
src/actionbar/babble/profiles/default/jsregistry.xml
src/actionbar/babble/profiles/default/metadata.xml