Metadata-Version: 1.0
Name: actionbar.babble
Version: 0.2
Summary: A actionbar.panel integration package for the Babble instant messaging system.
Home-page: http://plone.org/products/actionbar.babble/
Author: JC Brand, Syslab.com GmbH
Author-email: brand@syslab.com
License: GPL
Keywords: plone actionbar babble chat
Platform: UNKNOWN
Classifier: Framework :: Plone
Classifier: Programming Language :: Python
